WangLab/Constants.py
WangLab/__init__.py
WangLab/ChIP_seq/bowtie_ChIP_Seq.py
WangLab/ChIP_seq/cutadapt_ChIP_Seq.py
WangLab/ChIP_seq/macs.py
WangLab/RNA_seq/rna_seq.py
WangLab/Sequence_operate/calc_content.py
WangLab/Sequence_operate/calc_usage_deviation.py
WangLab/Sequence_operate/extract_seqs.py
WangLab/Sequence_operate/file_merge.py
WangLab/Sequence_operate/ossutil.py
WangLab/Sequence_operate/primer_blast.py
WangLab/Sequence_operate/primer_generator.py
WangLab/Sequence_operate/qPCR.py
WangLab/TIS/bowtie.py
WangLab/TIS/combine_reads.py
WangLab/TIS/count_reads.py
WangLab/TIS/cutadapt.py
WangLab-0.1.1.data/scripts/wanglab
WangLab-0.1.1.data/scripts/wanglab.bat
WangLab-0.1.1.dist-info/LICENSE
WangLab-0.1.1.dist-info/METADATA
WangLab-0.1.1.dist-info/WHEEL
WangLab-0.1.1.dist-info/top_level.txt
WangLab-0.1.1.dist-info/RECORD
